Metadata-Version: 2.4
Name: llama-index-embeddings-mixedbreadai
Version: 0.5.1
Summary: llama-index embeddings mixedbreadai integration
Author-email: Mixedbread AI <support@mixedbread.com>
License-Expression: MIT
License-File: LICENSE
Requires-Python: <4.0,>=3.9
Requires-Dist: llama-index-core<0.15,>=0.13.0
Requires-Dist: mixedbread<1,>=0.21.0
